Metadata-Version: 2.4
Name: AixWeather
Version: 0.2.0
Summary: A weather data generation tool for building energy system simulations.Pull, Transform, Export.
Home-page: https://github.com/RWTH-EBC/AixWeather
Download-URL: https://github.com/RWTH-EBC/AixWeather/archive/refs/tags/0.2.0.tar.gz
Author: RWTH Aachen University, E.ON Energy Research Center, Institute of Energy Efficient Buildings and Indoor Climate
Author-email: ebc-abos@eonerc.rwth-aachen.de
License: BSD 3-Clause
Keywords: weather,BES,converter,simulation,building,energy
Classifier: Development Status :: 3 - Alpha
Classifier: License :: OSI Approved :: BSD License
Classifier: Topic :: Scientific/Engineering
Classifier: Intended Audience :: Science/Research
Classifier: Programming Language :: Python :: 3.9
Classifier: Programming Language :: Python :: 3.10
Classifier: Programming Language :: Python :: 3.11
License-File: LICENSE
Requires-Dist: unidecode~=1.3.7
Requires-Dist: pvlib~=0.10.2
Requires-Dist: matplotlib~=3.8.1
Requires-Dist: seaborn~=0.13.0
Provides-Extra: try
Requires-Dist: geopandas~=0.14.0; extra == "try"
Requires-Dist: geopy~=2.4.0; extra == "try"
Requires-Dist: shapely~=2.0.3; extra == "try"
Provides-Extra: dwd-forecast
Requires-Dist: wetterdienst<=0.72.0,>=0.65.0; extra == "dwd-forecast"
Provides-Extra: full
Requires-Dist: wetterdienst<=0.72.0,>=0.65.0; extra == "full"
Requires-Dist: geopandas~=0.14.0; extra == "full"
Requires-Dist: geopy~=2.4.0; extra == "full"
Requires-Dist: shapely~=2.0.3; extra == "full"
Dynamic: author
Dynamic: author-email
Dynamic: classifier
Dynamic: description
Dynamic: description-content-type
Dynamic: download-url
Dynamic: home-page
Dynamic: keywords
Dynamic: license
Dynamic: license-file
Dynamic: provides-extra
Dynamic: requires-dist
Dynamic: summary
